hostfinder/__init__.py
hostfinder/py.typed
hostfinder/cli/__init__.py
hostfinder/cli/entry_point.py
hostfinder/main/__init__.py
hostfinder/main/hostfinder.py
hostfinder/main/main.py
hostfinder/models/__init__.py
hostfinder/models/address.py
hostfinder/models/options.py
hostfinder-1.0.2.dist-info/LICENSE
hostfinder-1.0.2.dist-info/METADATA
hostfinder-1.0.2.dist-info/WHEEL
hostfinder-1.0.2.dist-info/entry_points.txt
hostfinder-1.0.2.dist-info/top_level.txt
hostfinder-1.0.2.dist-info/RECORD
