Metadata-Version: 2.2
Name: hostfinder
Version: 1.0.2
Summary: Find hosts listening on specified port in local network
Author-email: Quinten Roets <qdr2104@columbia.edu>
License: MIT
Project-URL: Source Code, https://github.com/quintenroets/hostfinder
Requires-Python: >=3.10
License-File: LICENSE
Requires-Dist: package-utils<1,>=0.8.0
Requires-Dist: psutil<8,>=5.9.8
Provides-Extra: dev
Requires-Dist: hypothesis<7,>=6.100.0; extra == "dev"
Requires-Dist: package-dev-tools<1,>=0.5.11; extra == "dev"
Requires-Dist: package-dev-utils<2,>=0.1.6; extra == "dev"
Requires-Dist: types-psutil<8,>=5.9.5.20240316; extra == "dev"
